spiderfetch-0.4.9.data/scripts/spiderfetch
spiderfetch-0.4.9.dist-info/WHEEL
spiderfetch-0.4.9.dist-info/pydist.json
spiderfetch-0.4.9.dist-info/RECORD
spiderfetch-0.4.9.dist-info/DESCRIPTION.rst
spiderfetch-0.4.9.dist-info/METADATA
spiderfetch-0.4.9.dist-info/top_level.txt
spiderfetch-0.4.9.dist-info/entry_points.txt
spiderfetch/__init__.py
spiderfetch/ioutils.py
spiderfetch/spider.py
spiderfetch/filetype.py
spiderfetch/compat.py
spiderfetch/recipe.py
spiderfetch/fetch.py
spiderfetch/urlrewrite.py
spiderfetch/web.py
spiderfetch/spiderfetch.py
spiderfetch/dumpstream.py
spiderfetch/recipes/__init__.py
spiderfetch/recipes/jpg.py
spiderfetch/recipes/videostream.py
spiderfetch/recipes/mov.py
