Metadata-Version: 2.0
Name: spiderfetch
Version: 0.4.9
Summary: Web spider and fetcher
Home-page: https://github.com/numerodix/spiderfetch
Author: Martin Matusiak
Author-email: numerodix@gmail.com
License: UNKNOWN
Platform: UNKNOWN
Classifier: License :: OSI Approved :: GNU General Public License v2 (GPLv2)
Classifier: Programming Language :: Python :: 2.6
Classifier: Programming Language :: Python :: 2.7
Classifier: Programming Language :: Python :: 3
Classifier: Programming Language :: Python :: 3.2
Classifier: Programming Language :: Python :: 3.3
Classifier: Programming Language :: Python :: 3.4
Classifier: Programming Language :: Python :: Implementation :: CPython
Requires-Dist: ansicolor
